exemel.py
exemel-0.2.3.dist-info/LICENSE
exemel-0.2.3.dist-info/METADATA
exemel-0.2.3.dist-info/WHEEL
exemel-0.2.3.dist-info/top_level.txt
exemel-0.2.3.dist-info/RECORD
