Metadata-Version: 2.1
Name: exemel
Version: 0.2.3
Summary: Build XML documents easily and concisely using native Python data structures.
Home-page: https://github.com/aptbosox/exemel
Author: Alexander Thompson
Author-email: aptbosox@gmail.com
License: MIT
Platform: UNKNOWN
Classifier: Development Status :: 3 - Alpha
Classifier: Intended Audience :: Developers
Classifier: License :: OSI Approved :: MIT License
Classifier: Natural Language :: English
Classifier: Programming Language :: Python
Classifier: Programming Language :: Python :: 2
Classifier: Programming Language :: Python :: 2.7
Classifier: Programming Language :: Python :: 3
Classifier: Programming Language :: Python :: 3.5
Classifier: Programming Language :: Python :: 3.6
Classifier: Programming Language :: Python :: 3.7
Classifier: Programming Language :: Python :: 3.8
Classifier: Topic :: Software Development :: Libraries :: Python Modules
Requires-Dist: future (>=0.15.2)
Requires-Dist: lxml (>=3.0)
